MANIFEST.in
README.md
setup.py
cz11_skript/__init__.py
cz11_skript/hello_world.py
cz11_skript.egg-info/PKG-INFO
cz11_skript.egg-info/SOURCES.txt
cz11_skript.egg-info/dependency_links.txt
cz11_skript.egg-info/top_level.txt