Metadata-Version: 2.1
Name: cz11-skript
Version: 1.0.0
Summary: Testing package cz11
Home-page: UNKNOWN
Author: ja
Author-email: john.doe@gmail.com
License: UNKNOWN
Platform: UNKNOWN
